{
  "$schema": "https://json-schema.org/draft/2020-12/schema",
  "properties": {
    "collection_listing": {
      "properties": {
        "collection_id": {
          "type": "integer"
        },
        "sort_order": {
          "type": "integer"
        },
        "updated_at": {
          "format": "date-time",
          "type": "string"
        }
      },
      "required": [
        "collection_id"
      ],
      "type": "object"
    }
  },
  "required": [
    "collection_listing"
  ],
  "type": "object"
}